gpe_lib/__init__.py
gpe_lib/imports.py
gpe_lib/notebook/__init__.py
gpe_lib/notebook/colab.py
gpe_lib/notebook/jupyter.py
gpe_lib-0.0.7.dist-info/METADATA
gpe_lib-0.0.7.dist-info/WHEEL
gpe_lib-0.0.7.dist-info/top_level.txt
gpe_lib-0.0.7.dist-info/RECORD
