Metadata-Version: 2.4
Name: gpe_lib
Version: 0.0.7
Summary: Funcionalidades bem comumente usadas por mim
Author: Gustavo Exel
License-Expression: MIT
Requires-Dist: requests
Requires-Dist: matplotlib
Requires-Dist: numpy
Requires-Dist: pandas
